odoo/addons/product_code_unique/README.rst
odoo/addons/product_code_unique/__init__.py
odoo/addons/product_code_unique/__manifest__.py
odoo/addons/product_code_unique/models/__init__.py
odoo/addons/product_code_unique/models/product.py
odoo/addons/product_code_unique/static/description/icon.png
odoo11_addon_product_code_unique-11.0.1.0.0.dist-info/DESCRIPTION.rst
odoo11_addon_product_code_unique-11.0.1.0.0.dist-info/METADATA
odoo11_addon_product_code_unique-11.0.1.0.0.dist-info/RECORD
odoo11_addon_product_code_unique-11.0.1.0.0.dist-info/WHEEL
odoo11_addon_product_code_unique-11.0.1.0.0.dist-info/metadata.json
odoo11_addon_product_code_unique-11.0.1.0.0.dist-info/top_level.txt
